pointpp/__init__.py
pointpp/__main__.py
pointpp/driver.py
pointpp/gen.py
pointpp/method.py
pointpp/metric.py
pointpp/radpro.py
pointpp/solver.py
pointpp/util.py
pointpp/version.py
pointpp-0.2.1.dist-info/LICENSE
pointpp-0.2.1.dist-info/METADATA
pointpp-0.2.1.dist-info/WHEEL
pointpp-0.2.1.dist-info/entry_points.txt
pointpp-0.2.1.dist-info/top_level.txt
pointpp-0.2.1.dist-info/RECORD
