Metadata-Version: 2.1
Name: pointpp
Version: 0.2.1
Summary: Program to post-process verif files
Home-page: https://github.com/tnipen/pointpp
Author: Thomas Nipen
Author-email: thomas.nipen@met.no
License: BSD-3
Keywords: meteorology post-processing weather prediction
Platform: UNKNOWN
Classifier: Development Status :: 4 - Beta
Classifier: Intended Audience :: Science/Research
Classifier: Topic :: Scientific/Engineering :: Atmospheric Science
Classifier: Topic :: Scientific/Engineering :: Information Analysis
Classifier: License :: OSI Approved :: BSD License
Classifier: Programming Language :: Python :: 2
Classifier: Programming Language :: Python :: 2.6
Classifier: Programming Language :: Python :: 2.7
Classifier: Programming Language :: Python :: 3.6
Classifier: Programming Language :: Python :: 3.7
License-File: LICENSE
Requires-Dist: gridpp (>=0.6.0)
Requires-Dist: matplotlib
Requires-Dist: netCDF4
Requires-Dist: numpy (>=1.7)
Requires-Dist: scikit-learn
Requires-Dist: scipy
Requires-Dist: verif (>=1.0.0)
Provides-Extra: test
Requires-Dist: coverage ; extra == 'test'
Requires-Dist: pep8 ; extra == 'test'
